envsync/__init__.py
envsync/cli.py
envsync/hooks.py
envsync-0.1.1.dist-info/METADATA
envsync-0.1.1.dist-info/WHEEL
envsync-0.1.1.dist-info/entry_points.txt
envsync-0.1.1.dist-info/top_level.txt
envsync-0.1.1.dist-info/RECORD
