Metadata-Version: 2.1
Name: envsync
Version: 0.1.1
Summary: A tool to set up Git hooks for your target local git repo, that automatically synchronize and updates for requirements.txt and virtual environments, streamlining the process of managing development environment for projects.
Home-page: https://github.com/pakkinlau/envsync
Author: Pak Kin LAU
Author-email: pakkinlau.general@gmail.com
Classifier: Programming Language :: Python :: 3
Classifier: License :: OSI Approved :: MIT License
Classifier: Operating System :: OS Independent
Requires-Python: >=3.6
Requires-Dist: click
